boxcraft/__init__.py
boxcraft/probe.py
boxcraft/controller/__init__.py
boxcraft/controller/__main__.py
boxcraft/exceptions/__init__.py
boxcraft/exceptions/__main__.py
boxcraft/store/__init__.py
boxcraft/store/__main__.py
boxcraft-0.0.2.dist-info/LICENSE
boxcraft-0.0.2.dist-info/METADATA
boxcraft-0.0.2.dist-info/WHEEL
boxcraft-0.0.2.dist-info/top_level.txt
boxcraft-0.0.2.dist-info/RECORD
