Metadata-Version: 2.1
Name: boxcraft
Version: 0.0.2
Summary: Libreria para el Procesamiento Distribuido
Home-page: https://github.com/Lucho00Cuba/boxcraft
Author: JustMe
Author-email: lomv0209@gmail.com
Keywords: python box
Classifier: Development Status :: 3 - Alpha
Classifier: Intended Audience :: Developers
Classifier: License :: OSI Approved :: MIT License
Classifier: Programming Language :: Python :: 3
Classifier: Programming Language :: Python :: 3.6
Classifier: Programming Language :: Python :: 3.7
Classifier: Programming Language :: Python :: 3.8
Classifier: Programming Language :: Python :: 3.9
Classifier: Programming Language :: Python :: 3.10
Classifier: Operating System :: OS Independent
Requires-Python: >=3.6
License-File: LICENSE
Requires-Dist: async-timeout (==4.0.3)
Requires-Dist: redis (==4.6.0)
